octarver/__init__.py
octarver/__main__.py
octarver-0.1.3.dist-info/licenses/LICENSE
octarver-0.1.3.dist-info/METADATA
octarver-0.1.3.dist-info/WHEEL
octarver-0.1.3.dist-info/entry_points.txt
octarver-0.1.3.dist-info/top_level.txt
octarver-0.1.3.dist-info/RECORD
