Metadata-Version: 2.4
Name: octarver
Version: 0.1.3
Summary: Octave Range Converter - Convert between musical note names and frequencies
Author-email: Takayuki Kurosawa <tkuro11@gmail.com>
License: MIT
Project-URL: Homepage, https://github.com/tkuro11/octarver
Project-URL: Repository, https://github.com/tkuro11/octarver
Project-URL: Issues, https://github.com/tkuro11/octarver/issues
Project-URL: Documentation, https://github.com/tkuro11/octarver#readme
Keywords: music,audio,frequency,note,pitch,converter,octave
Classifier: Development Status :: 3 - Alpha
Classifier: Intended Audience :: Developers
Classifier: Intended Audience :: Education
Classifier: Intended Audience :: End Users/Desktop
Classifier: Topic :: Multimedia :: Sound/Audio :: Analysis
Classifier: License :: OSI Approved :: MIT License
Classifier: Operating System :: OS Independent
Classifier: Programming Language :: Python :: 3
Classifier: Programming Language :: Python :: 3.10
Classifier: Programming Language :: Python :: 3.11
Classifier: Programming Language :: Python :: 3.12
Requires-Python: >=3.10
License-File: LICENSE
Provides-Extra: dev
Requires-Dist: pytest>=9.0.2; extra == "dev"
Dynamic: license-file
